{
  "title": "Login • Instagram",
  "byline": null,
  "dir": null,
  "content": "<h2>Login • Instagram</h2><div id=\"readability-page-1\" class=\"page\"><div>\n<hr>\n<p>This article was downloaded by <strong>calibre</strong> from <a href=\"https://www.instagram.com/guardian_sport/\" rel=\"calibre-downloaded-from\">https://www.instagram.com/guardian_sport/</a></p>\n<p> | <a href=\"../index_u32.html#article_0\">段落菜单</a> | <a href=\"../../index_u23.html#feed_23\">主菜单</a> | </p></div></div>",
  "textContent": "\n\nThis article was downloaded by calibre from https://www.instagram.com/guardian_sport/\n | 段落菜单 | 主菜单 | ",
  "length": 104,
  "excerpt": "This article was downloaded by calibre from https://www.instagram.com/guardian_sport/",
  "siteName": null
}